textsum/__init__.py
textsum/app.py
textsum/cli.py
textsum/pdf2text.py
textsum/summarize.py
textsum/utils.py
textsum-0.2.2.dist-info/LICENSE
textsum-0.2.2.dist-info/METADATA
textsum-0.2.2.dist-info/WHEEL
textsum-0.2.2.dist-info/entry_points.txt
textsum-0.2.2.dist-info/top_level.txt
textsum-0.2.2.dist-info/RECORD
