Metadata-Version: 2.1
Name: textsum
Version: 0.2.2
Summary: utility for using transformers summarization models on text docs
Home-page: https://github.com/pszemraj/textsum
Author: peter szemraj
Author-email: peterszemraj+textsum@gmail.com
License: Apache-2.0
Project-URL: Documentation, https://github.com/pszemraj/textsum
Platform: any
Classifier: Development Status :: 4 - Beta
Classifier: Programming Language :: Python
Requires-Python: >=3.8
License-File: LICENSE
Requires-Dist: accelerate
Requires-Dist: clean-text
Requires-Dist: fire
Requires-Dist: natsort
Requires-Dist: nltk
Requires-Dist: torch >=2.0.0
Requires-Dist: tqdm
Requires-Dist: transformers >=4.46.0
Provides-Extra: 8bit
Requires-Dist: bitsandbytes ; extra == '8bit'
Requires-Dist: importlib-metadata ; python_version < "3.8"
Provides-Extra: pdf
Requires-Dist: python-doctr[torch] ; extra == 'pdf'
Requires-Dist: pyspellchecker ; extra == 'pdf'
Provides-Extra: all
Requires-Dist: gradio ; extra == 'all'
Requires-Dist: rapidfuzz ==2.13.7 ; extra == 'all'
Requires-Dist: python-doctr[torch] ; extra == 'all'
Requires-Dist: pyspellchecker ; extra == 'all'
Requires-Dist: optimum[exporters,onnxruntime] ; extra == 'all'
Requires-Dist: bitsandbytes ; extra == 'all'
Provides-Extra: app
Requires-Dist: gradio ; extra == 'app'
Requires-Dist: rapidfuzz ==2.13.7 ; extra == 'app'
Requires-Dist: python-doctr[torch] ; extra == 'app'
Requires-Dist: pyspellchecker ; extra == 'app'
Provides-Extra: optimum
Requires-Dist: optimum[exporters,onnxruntime] ; extra == 'optimum'
Provides-Extra: testing
Requires-Dist: setuptools ; extra == 'testing'
Requires-Dist: pytest ; extra == 'testing'
Requires-Dist: pytest-cov ; extra == 'testing'
Provides-Extra: unidecode
Requires-Dist: unidecode ; extra == 'unidecode'
